truthsayer/__init__.py
truthsayer/opti.py
truthsayer/poly.py
truthsayer/processor.py
truthsayer/renderer.py
truthsayer-0.10.10.dist-info/LICENSE
truthsayer-0.10.10.dist-info/METADATA
truthsayer-0.10.10.dist-info/WHEEL
truthsayer-0.10.10.dist-info/top_level.txt
truthsayer-0.10.10.dist-info/RECORD
