Metadata-Version: 2.1
Name: truthsayer
Version: 0.10.10
Summary: Visualizes and manages Dune the Board Game state
Home-page: https://github.com/marekyggdrasil/truthsayer
Author: Marek Narozniak
Author-email: marek.yggdrasil@gmail.com
License: MIT
Platform: UNKNOWN
Classifier: Programming Language :: Python :: 3
Classifier: Programming Language :: Python :: 2
Classifier: License :: OSI Approved :: MIT License
Classifier: Operating System :: OS Independent
License-File: LICENSE
Requires-Dist: pillow
Requires-Dist: qrcode
Requires-Dist: beautifulsoup4 (==4.8.1)
Requires-Dist: simpleai
Requires-Dist: brackette
Requires-Dist: shapely
